ChangeLog
LICENSE.txt
MANIFEST.in
Makefile
README.md
dockermon.py
run-tests.sh
setup.cfg
setup.py
test_dockermon.py
tox.ini
dockermon.egg-info/PKG-INFO
dockermon.egg-info/SOURCES.txt
dockermon.egg-info/dependency_links.txt
dockermon.egg-info/top_level.txt