Metadata-Version: 1.1
Name: dockermon
Version: 0.2.2
Summary: docker monitor using docker /events HTTP streaming API
Home-page: https://github.com/CyberInt/dockermon
Author: CyberInt
Author-email: tools@cyberint.com
License: MIT
Platform: UNKNOWN
Classifier: Development Status :: 4 - Beta
Classifier: Intended Audience :: Developers
Classifier: License :: OSI Approved :: MIT License
Classifier: Programming Language :: Python
Classifier: Programming Language :: Python :: 2
Classifier: Programming Language :: Python :: 3
Classifier: Topic :: Software Development :: Libraries
Classifier: Topic :: Software Development :: Libraries :: Python Modules
